{"credit":"Made with Blockbench","ambientocclusion":false,"texture_size":[64,64],"textures":{"0":"custom/plants/ancient/ancient_fern_2","particle":"custom/plants/ancient/ancient_fern_2"},"elements":[{"from":[3,0,8],"to":[13,0,32],"shade":false,"rotation":{"angle":-22.5,"axis":"x","origin":[8,0,8]},"faces":{"north":{"uv":[0,0,2.5,0],"rotation":180,"texture":"#0"},"east":{"uv":[0,0,0,6],"rotation":270,"texture":"#0"},"south":{"uv":[0,0,2.5,0],"texture":"#0"},"west":{"uv":[0,0,0,6],"rotation":90,"texture":"#0"},"up":{"uv":[0,0,2.5,6],"rotation":180,"texture":"#0"},"down":{"uv":[0,0,2.5,6],"texture":"#0"}}},{"from":[3,0,-16],"to":[13,0,8],"shade":false,"rotation":{"angle":22.5,"axis":"x","origin":[8,0,8]},"faces":{"north":{"uv":[0,0,2.5,0],"texture":"#0"},"east":{"uv":[0,0,0,6],"rotation":90,"texture":"#0"},"south":{"uv":[0,0,2.5,0],"rotation":180,"texture":"#0"},"west":{"uv":[0,0,0,6],"rotation":270,"texture":"#0"},"up":{"uv":[0,0,2.5,6],"texture":"#0"},"down":{"uv":[0,0,2.5,6],"rotation":180,"texture":"#0"}}},{"from":[-16,0,3],"to":[8,0,13],"shade":false,"rotation":{"angle":-22.5,"axis":"z","origin":[8,0,8]},"faces":{"north":{"uv":[0,0,0,6],"rotation":90,"texture":"#0"},"east":{"uv":[0,0,2.5,0],"rotation":180,"texture":"#0"},"south":{"uv":[0,0,0,6],"rotation":270,"texture":"#0"},"west":{"uv":[0,0,2.5,0],"texture":"#0"},"up":{"uv":[0,0,2.5,6],"rotation":270,"texture":"#0"},"down":{"uv":[0,0,2.5,6],"rotation":270,"texture":"#0"}}},{"from":[8,0,3],"to":[32,0,13],"shade":false,"rotation":{"angle":22.5,"axis":"z","origin":[8,0,8]},"faces":{"north":{"uv":[0,0,0,6],"rotation":270,"texture":"#0"},"east":{"uv":[0,0,2.5,0],"texture":"#0"},"south":{"uv":[0,0,0,6],"rotation":90,"texture":"#0"},"west":{"uv":[0,0,2.5,0],"rotation":180,"texture":"#0"},"up":{"uv":[2.5,6,0,0],"rotation":270,"texture":"#0"},"down":{"uv":[2.5,6,0,0],"rotation":270,"texture":"#0"}}},{"from":[3,0,8],"to":[13,20,8],"shade":false,"rotation":{"angle":45,"axis":"x","origin":[8,0,8]},"faces":{"north":{"uv":[2.75,0,5.25,5],"texture":"#0"},"east":{"uv":[0,0,0,5],"texture":"#missing"},"south":{"uv":[2.75,0,5.25,5],"texture":"#0"},"west":{"uv":[0,0,0,5],"texture":"#missing"},"up":{"uv":[0,0,2.5,0],"texture":"#missing"},"down":{"uv":[0,0,2.5,0],"texture":"#missing"}}},{"from":[3,0,8],"to":[13,20,8],"shade":false,"rotation":{"angle":-45,"axis":"x","origin":[8,0,8]},"faces":{"north":{"uv":[2.75,0,5.25,5],"texture":"#0"},"east":{"uv":[0,0,0,5],"texture":"#missing"},"south":{"uv":[2.75,0,5.25,5],"texture":"#0"},"west":{"uv":[0,0,0,5],"texture":"#missing"},"up":{"uv":[2.5,0,0,0],"texture":"#missing"},"down":{"uv":[2.5,0,0,0],"texture":"#missing"}}},{"from":[-3,0,8],"to":[17,32,8],"shade":false,"rotation":{"angle":45,"axis":"y","origin":[8,16,8]},"faces":{"north":{"uv":[7.5,0,12.5,8],"texture":"#0"},"east":{"uv":[0,0,0,8],"texture":"#missing"},"south":{"uv":[12.5,0,7.5,8],"texture":"#0"},"west":{"uv":[0,0,0,8],"texture":"#missing"},"up":{"uv":[0,0,4,0],"texture":"#missing"},"down":{"uv":[0,0,4,0],"texture":"#missing"}}}]}